{
	"file" : "..\\..\\src\\utils.cpp",
	"func" : "CleanCache::<lambda_d77eac45c7d1ed80b30fa3b7459de31f>::operator ()",
	"line" : 166,
	"message" : "cleaning \"D:\\OneDrive\\rawfulness-system\\collection-portable\\subtitlesae\\log\\*.json\"",
	"sec" : 1708694510,
	"section" : "utils/clean_cache",
	"severity" : 4,
	"usec" : 415921400
}{
	"file" : "..\\..\\libaegisub\\common\\io.cpp",
	"func" : "agi::io::Open",
	"line" : 34,
	"message" : "\"D:\\OneDrive\\rawfulness-system\\collection-portable\\subtitlesae\\config.json\"",
	"sec" : 1708694510,
	"section" : "agi/io/open/file",
	"severity" : 4,
	"usec" : 415921400
}{
	"file" : "..\\..\\src\\utils.cpp",
	"func" : "CleanCache::<lambda_d77eac45c7d1ed80b30fa3b7459de31f>::operator ()",
	"line" : 176,
	"message" : "cache does not need cleaning (maxsize=10485760, cursize=198336, maxfiles=100, numfiles=13), exiting",
	"sec" : 1708694510,
	"section" : "utils/clean_cache",
	"severity" : 4,
	"usec" : 416979900
}{
	"file" : "..\\..\\src\\command\\command.cpp",
	"func" : "cmd::init_builtin_commands",
	"line" : 80,
	"message" : "Populating command map",
	"sec" : 1708694510,
	"section" : "command/init",
	"severity" : 4,
	"usec" : 423019900
}{
	"file" : "..\\..\\libaegisub\\common\\hotkey.cpp",
	"func" : "agi::hotkey::Hotkey::Hotkey",
	"line" : 91,
	"message" : "Generating hotkeys.",
	"sec" : 1708694510,
	"section" : "hotkey/init",
	"severity" : 4,
	"usec" : 424016400
}{
	"file" : "..\\..\\libaegisub\\common\\io.cpp",
	"func" : "agi::io::Open",
	"line" : 34,
	"message" : "\"D:\\OneDrive\\rawfulness-system\\collection-portable\\subtitlesae\\hotkey.json\"",
	"sec" : 1708694510,
	"section" : "agi/io/open/file",
	"severity" : 4,
	"usec" : 424016400
}{
	"file" : "..\\..\\libaegisub\\common\\mru.cpp",
	"func" : "agi::MRUManager::MRUManager",
	"line" : 67,
	"message" : "Loading MRU List",
	"sec" : 1708694510,
	"section" : "agi/mru",
	"severity" : 4,
	"usec" : 425998700
}{
	"file" : "..\\..\\libaegisub\\common\\io.cpp",
	"func" : "agi::io::Open",
	"line" : 34,
	"message" : "\"D:\\OneDrive\\rawfulness-system\\collection-portable\\subtitlesae\\mru.json\"",
	"sec" : 1708694510,
	"section" : "agi/io/open/file",
	"severity" : 4,
	"usec" : 425998700
}{
	"file" : "..\\..\\src\\subtitles_provider_libass.cpp",
	"func" : "`anonymous-namespace'::msg_callback",
	"line" : 85,
	"message" : "Raster: FreeType 2.5.3",
	"sec" : 1708694510,
	"section" : "subtitle/provider/libass",
	"severity" : 4,
	"usec" : 427989800
}{
	"file" : "..\\..\\src\\subtitles_provider_libass.cpp",
	"func" : "`anonymous-namespace'::msg_callback",
	"line" : 85,
	"message" : "Shaper: FriBidi 0.19.6 (SIMPLE)",
	"sec" : 1708694510,
	"section" : "subtitle/provider/libass",
	"severity" : 4,
	"usec" : 429994800
}{
	"file" : "..\\..\\src\\subtitles_provider_libass.cpp",
	"func" : "`anonymous-namespace'::msg_callback",
	"line" : 85,
	"message" : "Initialized",
	"sec" : 1708694510,
	"section" : "subtitle/provider/libass",
	"severity" : 4,
	"usec" : 429994800
}{
	"file" : "..\\..\\src\\subtitles_provider_libass.cpp",
	"func" : "`anonymous-namespace'::msg_callback",
	"line" : 85,
	"message" : "No usable fontconfig configuration file found, using fallback.",
	"sec" : 1708694510,
	"section" : "subtitle/provider/libass",
	"severity" : 4,
	"usec" : 429994800
}{
	"file" : "..\\..\\src\\frame_main.cpp",
	"func" : "FrameMain::FrameMain",
	"line" : 100,
	"message" : "Entering FrameMain constructor",
	"sec" : 1708694510,
	"section" : "frame_main/init",
	"severity" : 3,
	"usec" : 477847600
}{
	"file" : "..\\..\\src\\frame_main.cpp",
	"func" : "FrameMain::FrameMain",
	"line" : 111,
	"message" : "Initializing context controls",
	"sec" : 1708694510,
	"section" : "frame_main/init",
	"severity" : 3,
	"usec" : 477847600
}{
	"file" : "..\\..\\src\\frame_main.cpp",
	"func" : "FrameMain::FrameMain",
	"line" : 118,
	"message" : "Initializing context frames",
	"sec" : 1708694510,
	"section" : "frame_main/init",
	"severity" : 3,
	"usec" : 477847600
}{
	"file" : "..\\..\\src\\frame_main.cpp",
	"func" : "FrameMain::FrameMain",
	"line" : 122,
	"message" : "Apply saved Maximized state",
	"sec" : 1708694510,
	"section" : "frame_main/init",
	"severity" : 3,
	"usec" : 477847600
}{
	"file" : "..\\..\\src\\frame_main.cpp",
	"func" : "FrameMain::FrameMain",
	"line" : 125,
	"message" : "Initialize toolbar",
	"sec" : 1708694510,
	"section" : "frame_main/init",
	"severity" : 3,
	"usec" : 477847600
}{
	"file" : "..\\..\\src\\frame_main.cpp",
	"func" : "FrameMain::FrameMain",
	"line" : 130,
	"message" : "Initialize menu bar",
	"sec" : 1708694510,
	"section" : "frame_main/init",
	"severity" : 3,
	"usec" : 580994800
}{
	"file" : "..\\..\\src\\frame_main.cpp",
	"func" : "FrameMain::FrameMain",
	"line" : 133,
	"message" : "Create status bar",
	"sec" : 1708694510,
	"section" : "frame_main/init",
	"severity" : 3,
	"usec" : 593952400
}{
	"file" : "..\\..\\src\\frame_main.cpp",
	"func" : "FrameMain::FrameMain",
	"line" : 136,
	"message" : "Set icon",
	"sec" : 1708694510,
	"section" : "frame_main/init",
	"severity" : 3,
	"usec" : 594948700
}{
	"file" : "..\\..\\src\\frame_main.cpp",
	"func" : "FrameMain::FrameMain",
	"line" : 145,
	"message" : "Create views and inner main window controls",
	"sec" : 1708694510,
	"section" : "frame_main/init",
	"severity" : 3,
	"usec" : 594948700
}{
	"file" : "..\\..\\src\\frame_main.cpp",
	"func" : "FrameMain::InitContents",
	"line" : 187,
	"message" : "Create background panel",
	"sec" : 1708694510,
	"section" : "frame_main/init",
	"severity" : 3,
	"usec" : 594948700
}{
	"file" : "..\\..\\src\\frame_main.cpp",
	"func" : "FrameMain::InitContents",
	"line" : 190,
	"message" : "Create subtitles grid",
	"sec" : 1708694510,
	"section" : "frame_main/init",
	"severity" : 3,
	"usec" : 595947600
}{
	"file" : "..\\..\\src\\frame_main.cpp",
	"func" : "FrameMain::InitContents",
	"line" : 193,
	"message" : "Create video box",
	"sec" : 1708694510,
	"section" : "frame_main/init",
	"severity" : 3,
	"usec" : 599932300
}{
	"file" : "..\\..\\src\\frame_main.cpp",
	"func" : "FrameMain::InitContents",
	"line" : 196,
	"message" : "Create audio box",
	"sec" : 1708694510,
	"section" : "frame_main/init",
	"severity" : 3,
	"usec" : 760735400
}{
	"file" : "..\\..\\src\\frame_main.cpp",
	"func" : "FrameMain::InitContents",
	"line" : 199,
	"message" : "Create subtitle editing box",
	"sec" : 1708694510,
	"section" : "frame_main/init",
	"severity" : 3,
	"usec" : 798690400
}{
	"file" : "..\\..\\src\\spellchecker_hunspell.cpp",
	"func" : "HunspellSpellChecker::OnLanguageChanged",
	"line" : 197,
	"message" : "\"D:\\OneDrive\\rawfulness-system\\collection-portable\\subtitlesae\\dictionaries\\en_US.dic\"",
	"sec" : 1708694510,
	"section" : "dictionary/file",
	"severity" : 3,
	"usec" : 845268000
}{
	"file" : "..\\..\\libaegisub\\common\\io.cpp",
	"func" : "agi::io::Open",
	"line" : 34,
	"message" : "\"D:\\OneDrive\\rawfulness-system\\collection-portable\\subtitlesae\\dictionaries\\user_en_US.dic\"",
	"sec" : 1708694510,
	"section" : "agi/io/open/file",
	"severity" : 4,
	"usec" : 890625900
}{
	"file" : "..\\..\\src\\frame_main.cpp",
	"func" : "FrameMain::InitContents",
	"line" : 202,
	"message" : "Arrange main sizers",
	"sec" : 1708694510,
	"section" : "frame_main/init",
	"severity" : 3,
	"usec" : 930846500
}{
	"file" : "..\\..\\src\\frame_main.cpp",
	"func" : "FrameMain::InitContents",
	"line" : 215,
	"message" : "Perform layout",
	"sec" : 1708694510,
	"section" : "frame_main/init",
	"severity" : 3,
	"usec" : 931840700
}{
	"file" : "..\\..\\src\\frame_main.cpp",
	"func" : "FrameMain::InitContents",
	"line" : 217,
	"message" : "Leaving InitContents",
	"sec" : 1708694510,
	"section" : "frame_main/init",
	"severity" : 3,
	"usec" : 931840700
}{
	"file" : "..\\..\\src\\frame_main.cpp",
	"func" : "FrameMain::FrameMain",
	"line" : 149,
	"message" : "Set up drag/drop target",
	"sec" : 1708694510,
	"section" : "frame_main/init",
	"severity" : 3,
	"usec" : 931840700
}{
	"file" : "..\\..\\src\\frame_main.cpp",
	"func" : "FrameMain::FrameMain",
	"line" : 152,
	"message" : "Load default file",
	"sec" : 1708694510,
	"section" : "frame_main/init",
	"severity" : 3,
	"usec" : 932837000
}{
	"file" : "..\\..\\src\\frame_main.cpp",
	"func" : "FrameMain::FrameMain",
	"line" : 155,
	"message" : "Display main window",
	"sec" : 1708694510,
	"section" : "frame_main/init",
	"severity" : 3,
	"usec" : 943801200
}{
	"file" : "..\\..\\src\\frame_main.cpp",
	"func" : "FrameMain::FrameMain",
	"line" : 160,
	"message" : "Leaving FrameMain constructor",
	"sec" : 1708694511,
	"section" : "frame_main/init",
	"severity" : 3,
	"usec" : 59888400
}{
	"file" : "..\\..\\src\\utils.cpp",
	"func" : "CleanCache::<lambda_d77eac45c7d1ed80b30fa3b7459de31f>::operator ()",
	"line" : 166,
	"message" : "cleaning \"D:\\OneDrive\\rawfulness-system\\collection-portable\\subtitlesae\\autosave\\*.AUTOSAVE.ass\"",
	"sec" : 1708694511,
	"section" : "utils/clean_cache",
	"severity" : 4,
	"usec" : 59888400
}{
	"file" : "..\\..\\src\\utils.cpp",
	"func" : "CleanCache::<lambda_d77eac45c7d1ed80b30fa3b7459de31f>::operator ()",
	"line" : 176,
	"message" : "cache does not need cleaning (maxsize=104857600, cursize=1691696, maxfiles=1000, numfiles=15), exiting",
	"sec" : 1708694511,
	"section" : "utils/clean_cache",
	"severity" : 4,
	"usec" : 62877600
}{
	"file" : "..\\..\\src\\charset_detect.cpp",
	"func" : "CharSetDetect::GetEncoding",
	"line" : 62,
	"message" : "\"D:\\OneDrive - Rawfulness\\rawfulness-cinematic\\filmcine\\[2004] the bourne supremacy.srt\" (UTF-8)",
	"sec" : 1708694514,
	"section" : "charset/file",
	"severity" : 3,
	"usec" : 565843800
}{
	"file" : "..\\..\\libaegisub\\common\\io.cpp",
	"func" : "agi::io::Open",
	"line" : 34,
	"message" : "\"D:\\OneDrive - Rawfulness\\rawfulness-cinematic\\filmcine\\[2004] the bourne supremacy.srt\"",
	"sec" : 1708694514,
	"section" : "agi/io/open/file",
	"severity" : 4,
	"usec" : 565843800
}{
	"file" : "..\\..\\libaegisub\\common\\io.cpp",
	"func" : "agi::io::Open",
	"line" : 34,
	"message" : "\"D:\\OneDrive - Rawfulness\\rawfulness-cinematic\\filmcine\\[2004] the bourne supremacy.srt\"",
	"sec" : 1708694514,
	"section" : "agi/io/open/file",
	"severity" : 4,
	"usec" : 565843800
}{
	"file" : "..\\..\\libaegisub\\common\\io.cpp",
	"func" : "agi::io::Open",
	"line" : 34,
	"message" : "\"D:\\OneDrive\\rawfulness-system\\collection-portable\\subtitlesae\\shift_history.json\"",
	"sec" : 1708694521,
	"section" : "agi/io/open/file",
	"severity" : 4,
	"usec" : 444405500
}{
	"file" : "..\\..\\libaegisub\\common\\io.cpp",
	"func" : "agi::io::Save::Save",
	"line" : 49,
	"message" : "\"D:\\OneDrive\\rawfulness-system\\collection-portable\\subtitlesae\\shift_history.json\"",
	"sec" : 1708694524,
	"section" : "agi/io/save/file",
	"severity" : 4,
	"usec" : 925217200
}{
	"file" : "..\\..\\libaegisub\\common\\io.cpp",
	"func" : "agi::io::Save::Save",
	"line" : 49,
	"message" : "\"D:\\OneDrive - Rawfulness\\rawfulness-cinematic\\filmcine\\[2004] the bourne supremacy.srt\"",
	"sec" : 1708694537,
	"section" : "agi/io/save/file",
	"severity" : 4,
	"usec" : 68908300
}{
	"file" : "..\\..\\libaegisub\\common\\io.cpp",
	"func" : "agi::io::Save::Save",
	"line" : 49,
	"message" : "\"D:\\OneDrive\\rawfulness-system\\collection-portable\\subtitlesae\\autosave\\[2004] the bourne supremacy.srt.2024-02-23-20-22-50.AUTOSAVE.ass\"",
	"sec" : 1708694570,
	"section" : "agi/io/save/file",
	"severity" : 4,
	"usec" : 488629100
}{
	"file" : "..\\..\\libaegisub\\common\\hotkey.cpp",
	"func" : "agi::hotkey::Hotkey::Scan",
	"line" : 132,
	"message" : "Found: Ctrl-Z  Context (req/found): Subtitle Grid/Default   Command: edit/undo",
	"sec" : 1708694574,
	"section" : "agi/hotkey/found",
	"severity" : 4,
	"usec" : 145523400
}{
	"file" : "..\\..\\libaegisub\\common\\hotkey.cpp",
	"func" : "agi::hotkey::Hotkey::Scan",
	"line" : 132,
	"message" : "Found: Ctrl-Z  Context (req/found): Subtitle Grid/Default   Command: edit/undo",
	"sec" : 1708694577,
	"section" : "agi/hotkey/found",
	"severity" : 4,
	"usec" : 466266300
}{
	"file" : "..\\..\\libaegisub\\common\\io.cpp",
	"func" : "agi::io::Open",
	"line" : 34,
	"message" : "\"D:\\OneDrive\\rawfulness-system\\collection-portable\\subtitlesae\\shift_history.json\"",
	"sec" : 1708694579,
	"section" : "agi/io/open/file",
	"severity" : 4,
	"usec" : 809842900
}{
	"file" : "..\\..\\libaegisub\\common\\io.cpp",
	"func" : "agi::io::Save::Save",
	"line" : 49,
	"message" : "\"D:\\OneDrive\\rawfulness-system\\collection-portable\\subtitlesae\\shift_history.json\"",
	"sec" : 1708694581,
	"section" : "agi/io/save/file",
	"severity" : 4,
	"usec" : 594155100
}{
	"file" : "..\\..\\src\\video_provider_manager.cpp",
	"func" : "VideoProviderFactory::GetProvider",
	"line" : 94,
	"message" : "YUV4MPEG: video is not in a supported format.",
	"sec" : 1708694592,
	"section" : "manager/video/provider",
	"severity" : 4,
	"usec" : 666491400
}{
	"file" : "..\\..\\libaegisub\\common\\io.cpp",
	"func" : "agi::io::Save::Save",
	"line" : 49,
	"message" : "\"D:\\OneDrive\\rawfulness-system\\collection-portable\\subtitlesae\\autosave\\[2004] the bourne supremacy.srt.2024-02-23-20-23-50.AUTOSAVE.ass\"",
	"sec" : 1708694630,
	"section" : "agi/io/save/file",
	"severity" : 4,
	"usec" : 485596100
}{
	"file" : "..\\..\\src\\utils.cpp",
	"func" : "CleanCache::<lambda_d77eac45c7d1ed80b30fa3b7459de31f>::operator ()",
	"line" : 166,
	"message" : "cleaning \"D:\\OneDrive\\rawfulness-system\\collection-portable\\subtitlesae\\ffms2cache\\*.ffindex\"",
	"sec" : 1708694666,
	"section" : "utils/clean_cache",
	"severity" : 4,
	"usec" : 87950300
}{
	"file" : "..\\..\\src\\utils.cpp",
	"func" : "CleanCache::<lambda_d77eac45c7d1ed80b30fa3b7459de31f>::operator ()",
	"line" : 176,
	"message" : "cache does not need cleaning (maxsize=44040192, cursize=3769512, maxfiles=20, numfiles=3), exiting",
	"sec" : 1708694666,
	"section" : "utils/clean_cache",
	"severity" : 4,
	"usec" : 93451400
}{
	"file" : "..\\..\\src\\video_provider_manager.cpp",
	"func" : "VideoProviderFactory::GetProvider",
	"line" : 72,
	"message" : "FFmpegSource: opened \"D:\\OneDrive - Rawfulness\\rawfulness-cinematic\\filmcine\\[2004] the bourne supremacy.mkv\"",
	"sec" : 1708694666,
	"section" : "manager/video/provider",
	"severity" : 3,
	"usec" : 305840000
}{
	"file" : "..\\..\\libaegisub\\common\\io.cpp",
	"func" : "agi::io::Save::Save",
	"line" : 49,
	"message" : "\"D:\\OneDrive\\rawfulness-system\\collection-portable\\subtitlesae\\mru.json\"",
	"sec" : 1708694666,
	"section" : "agi/io/save/file",
	"severity" : 4,
	"usec" : 468195200
}{
	"file" : "..\\..\\src\\audio_provider_factory.cpp",
	"func" : "GetAudioProvider",
	"line" : 80,
	"message" : "RIFF PCM WAV audio provider: File is not a RIFF file\nWave64 audio provider: File is not a RIFF file",
	"sec" : 1708694666,
	"section" : "audio_provider",
	"severity" : 4,
	"usec" : 681847600
}{
	"file" : "..\\..\\src\\audio_provider_factory.cpp",
	"func" : "GetAudioProvider",
	"line" : 72,
	"message" : "Using audio provider: FFmpegSource",
	"sec" : 1708694667,
	"section" : "audio_provider",
	"severity" : 3,
	"usec" : 117841000
}{
	"file" : "..\\..\\libaegisub\\common\\io.cpp",
	"func" : "agi::io::Save::Save",
	"line" : 49,
	"message" : "\"D:\\OneDrive\\rawfulness-system\\collection-portable\\subtitlesae\\mru.json\"",
	"sec" : 1708694667,
	"section" : "agi/io/save/file",
	"severity" : 4,
	"usec" : 372372500
}{
	"file" : "..\\..\\src\\video_out_gl.cpp",
	"func" : "VideoOutGL::InitTextures",
	"line" : 105,
	"message" : "Video size: 1920x816",
	"sec" : 1708694667,
	"section" : "video/out/gl",
	"severity" : 3,
	"usec" : 653618700
}{
	"file" : "..\\..\\src\\video_out_gl.cpp",
	"func" : "TestTexture",
	"line" : 67,
	"message" : "VideoOutGL::TestTexture: 64x64",
	"sec" : 1708694667,
	"section" : "video/out/gl",
	"severity" : 3,
	"usec" : 655923100
}{
	"file" : "..\\..\\src\\video_out_gl.cpp",
	"func" : "TestTexture",
	"line" : 67,
	"message" : "VideoOutGL::TestTexture: 16384x16384",
	"sec" : 1708694667,
	"section" : "video/out/gl",
	"severity" : 3,
	"usec" : 655923100
}{
	"file" : "..\\..\\src\\video_out_gl.cpp",
	"func" : "VideoOutGL::DetectOpenGLCapabilities",
	"line" : 85,
	"message" : "Maximum texture size is 16384x16384",
	"sec" : 1708694667,
	"section" : "video/out/gl",
	"severity" : 3,
	"usec" : 655923100
}{
	"file" : "..\\..\\src\\video_out_gl.cpp",
	"func" : "TestTexture",
	"line" : 67,
	"message" : "VideoOutGL::TestTexture: 16384x8192",
	"sec" : 1708694667,
	"section" : "video/out/gl",
	"severity" : 3,
	"usec" : 655923100
}{
	"file" : "..\\..\\src\\video_out_gl.cpp",
	"func" : "VideoOutGL::InitTextures",
	"line" : 236,
	"message" : "Using texture size: 2048x1024",
	"sec" : 1708694667,
	"section" : "video/out/gl",
	"severity" : 3,
	"usec" : 656977900
}{
	"file" : "..\\..\\src\\audio_player_dsound2.cpp",
	"func" : "`anonymous-namespace'::DirectSoundPlayer2Thread::Play",
	"line" : 720,
	"message" : "Playback begun",
	"sec" : 1708694671,
	"section" : "audio/player/dsound",
	"severity" : 4,
	"usec" : 381256200
}{
	"file" : "..\\..\\libaegisub\\common\\hotkey.cpp",
	"func" : "agi::hotkey::Hotkey::Scan",
	"line" : 128,
	"message" : "Found: Space  Context: Audio  Command: audio/play/selection",
	"sec" : 1708694684,
	"section" : "agi/hotkey/found",
	"severity" : 4,
	"usec" : 749962200
}{
	"file" : "..\\..\\src\\audio_player_dsound2.cpp",
	"func" : "`anonymous-namespace'::DirectSoundPlayer2Thread::Play",
	"line" : 720,
	"message" : "Playback begun",
	"sec" : 1708694684,
	"section" : "audio/player/dsound",
	"severity" : 4,
	"usec" : 749962200
}{
	"file" : "..\\..\\libaegisub\\common\\io.cpp",
	"func" : "agi::io::Save::Save",
	"line" : 49,
	"message" : "\"D:\\OneDrive\\rawfulness-system\\collection-portable\\subtitlesae\\autosave\\[2004] the bourne supremacy.srt.2024-02-23-20-24-50.AUTOSAVE.ass\"",
	"sec" : 1708694690,
	"section" : "agi/io/save/file",
	"severity" : 4,
	"usec" : 496919000
}{
	"file" : "..\\..\\libaegisub\\common\\hotkey.cpp",
	"func" : "agi::hotkey::Hotkey::Scan",
	"line" : 128,
	"message" : "Found: Space  Context: Audio  Command: audio/play/selection",
	"sec" : 1708694690,
	"section" : "agi/hotkey/found",
	"severity" : 4,
	"usec" : 657333100
}{
	"file" : "..\\..\\src\\audio_player_dsound2.cpp",
	"func" : "`anonymous-namespace'::DirectSoundPlayer2Thread::Play",
	"line" : 720,
	"message" : "Playback begun",
	"sec" : 1708694690,
	"section" : "audio/player/dsound",
	"severity" : 4,
	"usec" : 657333100
}{
	"file" : "..\\..\\src\\audio_player_dsound2.cpp",
	"func" : "`anonymous-namespace'::DirectSoundPlayer2Thread::Play",
	"line" : 720,
	"message" : "Playback begun",
	"sec" : 1708694695,
	"section" : "audio/player/dsound",
	"severity" : 4,
	"usec" : 822094500
}{
	"file" : "..\\..\\libaegisub\\common\\hotkey.cpp",
	"func" : "agi::hotkey::Hotkey::Scan",
	"line" : 128,
	"message" : "Found: Space  Context: Audio  Command: audio/play/selection",
	"sec" : 1708694734,
	"section" : "agi/hotkey/found",
	"severity" : 4,
	"usec" : 294014600
}{
	"file" : "..\\..\\src\\audio_player_dsound2.cpp",
	"func" : "`anonymous-namespace'::DirectSoundPlayer2Thread::Play",
	"line" : 720,
	"message" : "Playback begun",
	"sec" : 1708694734,
	"section" : "audio/player/dsound",
	"severity" : 4,
	"usec" : 294014600
}{
	"file" : "..\\..\\libaegisub\\common\\hotkey.cpp",
	"func" : "agi::hotkey::Hotkey::Scan",
	"line" : 128,
	"message" : "Found: Space  Context: Audio  Command: audio/play/selection",
	"sec" : 1708694735,
	"section" : "agi/hotkey/found",
	"severity" : 4,
	"usec" : 935457200
}{
	"file" : "..\\..\\src\\audio_player_dsound2.cpp",
	"func" : "`anonymous-namespace'::DirectSoundPlayer2Thread::Play",
	"line" : 720,
	"message" : "Playback begun",
	"sec" : 1708694735,
	"section" : "audio/player/dsound",
	"severity" : 4,
	"usec" : 935457200
}{
	"file" : "..\\..\\libaegisub\\common\\hotkey.cpp",
	"func" : "agi::hotkey::Hotkey::Scan",
	"line" : 128,
	"message" : "Found: Space  Context: Audio  Command: audio/play/selection",
	"sec" : 1708694736,
	"section" : "agi/hotkey/found",
	"severity" : 4,
	"usec" : 766731800
}{
	"file" : "..\\..\\src\\audio_player_dsound2.cpp",
	"func" : "`anonymous-namespace'::DirectSoundPlayer2Thread::Play",
	"line" : 720,
	"message" : "Playback begun",
	"sec" : 1708694736,
	"section" : "audio/player/dsound",
	"severity" : 4,
	"usec" : 766731800
}{
	"file" : "..\\..\\libaegisub\\common\\hotkey.cpp",
	"func" : "agi::hotkey::Hotkey::Scan",
	"line" : 128,
	"message" : "Found: Space  Context: Audio  Command: audio/play/selection",
	"sec" : 1708694737,
	"section" : "agi/hotkey/found",
	"severity" : 4,
	"usec" : 714222100
}{
	"file" : "..\\..\\src\\audio_player_dsound2.cpp",
	"func" : "`anonymous-namespace'::DirectSoundPlayer2Thread::Play",
	"line" : 720,
	"message" : "Playback begun",
	"sec" : 1708694737,
	"section" : "audio/player/dsound",
	"severity" : 4,
	"usec" : 714222100
}{
	"file" : "..\\..\\libaegisub\\common\\hotkey.cpp",
	"func" : "agi::hotkey::Hotkey::Scan",
	"line" : 128,
	"message" : "Found: Space  Context: Audio  Command: audio/play/selection",
	"sec" : 1708694750,
	"section" : "agi/hotkey/found",
	"severity" : 4,
	"usec" : 1900400
}{
	"file" : "..\\..\\src\\audio_player_dsound2.cpp",
	"func" : "`anonymous-namespace'::DirectSoundPlayer2Thread::Play",
	"line" : 720,
	"message" : "Playback begun",
	"sec" : 1708694750,
	"section" : "audio/player/dsound",
	"severity" : 4,
	"usec" : 1900400
}{
	"file" : "..\\..\\libaegisub\\common\\hotkey.cpp",
	"func" : "agi::hotkey::Hotkey::Scan",
	"line" : 128,
	"message" : "Found: Space  Context: Audio  Command: audio/play/selection",
	"sec" : 1708694750,
	"section" : "agi/hotkey/found",
	"severity" : 4,
	"usec" : 963892900
}{
	"file" : "..\\..\\src\\audio_player_dsound2.cpp",
	"func" : "`anonymous-namespace'::DirectSoundPlayer2Thread::Play",
	"line" : 720,
	"message" : "Playback begun",
	"sec" : 1708694750,
	"section" : "audio/player/dsound",
	"severity" : 4,
	"usec" : 963892900
}{
	"file" : "..\\..\\src\\audio_player_dsound2.cpp",
	"func" : "`anonymous-namespace'::DirectSoundPlayer2Thread::Play",
	"line" : 720,
	"message" : "Playback begun",
	"sec" : 1708694767,
	"section" : "audio/player/dsound",
	"severity" : 4,
	"usec" : 335672000
}{
	"file" : "..\\..\\libaegisub\\common\\hotkey.cpp",
	"func" : "agi::hotkey::Hotkey::Scan",
	"line" : 128,
	"message" : "Found: Space  Context: Audio  Command: audio/play/selection",
	"sec" : 1708694781,
	"section" : "agi/hotkey/found",
	"severity" : 4,
	"usec" : 815122800
}{
	"file" : "..\\..\\src\\audio_player_dsound2.cpp",
	"func" : "`anonymous-namespace'::DirectSoundPlayer2Thread::Play",
	"line" : 720,
	"message" : "Playback begun",
	"sec" : 1708694781,
	"section" : "audio/player/dsound",
	"severity" : 4,
	"usec" : 815122800
}{
	"file" : "..\\..\\libaegisub\\common\\hotkey.cpp",
	"func" : "agi::hotkey::Hotkey::Scan",
	"line" : 128,
	"message" : "Found: Space  Context: Audio  Command: audio/play/selection",
	"sec" : 1708694786,
	"section" : "agi/hotkey/found",
	"severity" : 4,
	"usec" : 941292700
}{
	"file" : "..\\..\\src\\audio_player_dsound2.cpp",
	"func" : "`anonymous-namespace'::DirectSoundPlayer2Thread::Play",
	"line" : 720,
	"message" : "Playback begun",
	"sec" : 1708694786,
	"section" : "audio/player/dsound",
	"severity" : 4,
	"usec" : 941292700
}{
	"file" : "..\\..\\libaegisub\\common\\io.cpp",
	"func" : "agi::io::Open",
	"line" : 34,
	"message" : "\"D:\\OneDrive\\rawfulness-system\\collection-portable\\subtitlesae\\shift_history.json\"",
	"sec" : 1708694791,
	"section" : "agi/io/open/file",
	"severity" : 4,
	"usec" : 139593400
}{
	"file" : "..\\..\\libaegisub\\common\\io.cpp",
	"func" : "agi::io::Save::Save",
	"line" : 49,
	"message" : "\"D:\\OneDrive\\rawfulness-system\\collection-portable\\subtitlesae\\shift_history.json\"",
	"sec" : 1708694799,
	"section" : "agi/io/save/file",
	"severity" : 4,
	"usec" : 469367500
}{
	"file" : "..\\..\\libaegisub\\common\\hotkey.cpp",
	"func" : "agi::hotkey::Hotkey::Scan",
	"line" : 132,
	"message" : "Found: Ctrl-Z  Context (req/found): Subtitle Grid/Default   Command: edit/undo",
	"sec" : 1708694801,
	"section" : "agi/hotkey/found",
	"severity" : 4,
	"usec" : 267469200
}{
	"file" : "..\\..\\libaegisub\\common\\io.cpp",
	"func" : "agi::io::Open",
	"line" : 34,
	"message" : "\"D:\\OneDrive\\rawfulness-system\\collection-portable\\subtitlesae\\shift_history.json\"",
	"sec" : 1708694804,
	"section" : "agi/io/open/file",
	"severity" : 4,
	"usec" : 59230100
}{
	"file" : "..\\..\\libaegisub\\common\\io.cpp",
	"func" : "agi::io::Save::Save",
	"line" : 49,
	"message" : "\"D:\\OneDrive\\rawfulness-system\\collection-portable\\subtitlesae\\shift_history.json\"",
	"sec" : 1708694805,
	"section" : "agi/io/save/file",
	"severity" : 4,
	"usec" : 824041500
}{
	"file" : "..\\..\\src\\audio_player_dsound2.cpp",
	"func" : "`anonymous-namespace'::DirectSoundPlayer2Thread::Play",
	"line" : 720,
	"message" : "Playback begun",
	"sec" : 1708694807,
	"section" : "audio/player/dsound",
	"severity" : 4,
	"usec" : 919474500
}{
	"file" : "..\\..\\libaegisub\\common\\io.cpp",
	"func" : "agi::io::Save::Save",
	"line" : 49,
	"message" : "\"D:\\OneDrive\\rawfulness-system\\collection-portable\\subtitlesae\\autosave\\[2004] the bourne supremacy.srt.2024-02-23-20-26-50.AUTOSAVE.ass\"",
	"sec" : 1708694810,
	"section" : "agi/io/save/file",
	"severity" : 4,
	"usec" : 504781500
}{
	"file" : "..\\..\\libaegisub\\common\\hotkey.cpp",
	"func" : "agi::hotkey::Hotkey::Scan",
	"line" : 128,
	"message" : "Found: Space  Context: Audio  Command: audio/play/selection",
	"sec" : 1708694812,
	"section" : "agi/hotkey/found",
	"severity" : 4,
	"usec" : 269543100
}{
	"file" : "..\\..\\src\\audio_player_dsound2.cpp",
	"func" : "`anonymous-namespace'::DirectSoundPlayer2Thread::Play",
	"line" : 720,
	"message" : "Playback begun",
	"sec" : 1708694812,
	"section" : "audio/player/dsound",
	"severity" : 4,
	"usec" : 269543100
}{
	"file" : "..\\..\\src\\audio_player_dsound2.cpp",
	"func" : "`anonymous-namespace'::DirectSoundPlayer2Thread::Play",
	"line" : 720,
	"message" : "Playback begun",
	"sec" : 1708694816,
	"section" : "audio/player/dsound",
	"severity" : 4,
	"usec" : 239416600
}{
	"file" : "..\\..\\src\\audio_player_dsound2.cpp",
	"func" : "`anonymous-namespace'::DirectSoundPlayer2Thread::Play",
	"line" : 720,
	"message" : "Playback begun",
	"sec" : 1708694851,
	"section" : "audio/player/dsound",
	"severity" : 4,
	"usec" : 149682800
}{
	"file" : "..\\..\\src\\audio_player_dsound2.cpp",
	"func" : "`anonymous-namespace'::DirectSoundPlayer2Thread::Play",
	"line" : 720,
	"message" : "Playback begun",
	"sec" : 1708694863,
	"section" : "audio/player/dsound",
	"severity" : 4,
	"usec" : 727346100
}{
	"file" : "..\\..\\src\\audio_player_dsound2.cpp",
	"func" : "`anonymous-namespace'::DirectSoundPlayer2Thread::Play",
	"line" : 720,
	"message" : "Playback begun",
	"sec" : 1708694875,
	"section" : "audio/player/dsound",
	"severity" : 4,
	"usec" : 184123300
}{
	"file" : "..\\..\\libaegisub\\common\\io.cpp",
	"func" : "agi::io::Save::Save",
	"line" : 49,
	"message" : "\"D:\\OneDrive - Rawfulness\\rawfulness-cinematic\\filmcine\\[2004] the bourne supremacy.srt\"",
	"sec" : 1708694899,
	"section" : "agi/io/save/file",
	"severity" : 4,
	"usec" : 96814100
}{
	"file" : "..\\..\\libaegisub\\common\\io.cpp",
	"func" : "agi::io::Save::Save",
	"line" : 49,
	"message" : "\"D:\\OneDrive\\rawfulness-system\\collection-portable\\subtitlesae\\config.json\"",
	"sec" : 1708694902,
	"section" : "agi/io/save/file",
	"severity" : 4,
	"usec" : 341728600
}{
	"file" : "..\\..\\src\\auto4_lua_assfile.cpp",
	"func" : "Automation4::LuaAssFile::ObjectGarbageCollect",
	"line" : 591,
	"message" : "Garbage collected LuaAssFile",
	"sec" : 1708694902,
	"section" : "automation/lua",
	"severity" : 4,
	"usec" : 351690900
}{
	"file" : "..\\..\\src\\auto4_lua_assfile.cpp",
	"func" : "Automation4::LuaAssFile::ObjectGarbageCollect",
	"line" : 591,
	"message" : "Garbage collected LuaAssFile",
	"sec" : 1708694902,
	"section" : "automation/lua",
	"severity" : 4,
	"usec" : 351690900
}{
	"file" : "..\\..\\src\\auto4_lua_assfile.cpp",
	"func" : "Automation4::LuaAssFile::ObjectGarbageCollect",
	"line" : 591,
	"message" : "Garbage collected LuaAssFile",
	"sec" : 1708694902,
	"section" : "automation/lua",
	"severity" : 4,
	"usec" : 351690900
}{
	"file" : "..\\..\\src\\auto4_lua_assfile.cpp",
	"func" : "Automation4::LuaAssFile::ObjectGarbageCollect",
	"line" : 591,
	"message" : "Garbage collected LuaAssFile",
	"sec" : 1708694902,
	"section" : "automation/lua",
	"severity" : 4,
	"usec" : 351690900
}{
	"file" : "..\\..\\src\\auto4_lua_assfile.cpp",
	"func" : "Automation4::LuaAssFile::ObjectGarbageCollect",
	"line" : 591,
	"message" : "Garbage collected LuaAssFile",
	"sec" : 1708694902,
	"section" : "automation/lua",
	"severity" : 4,
	"usec" : 351690900
}{
	"file" : "..\\..\\src\\auto4_lua_assfile.cpp",
	"func" : "Automation4::LuaAssFile::ObjectGarbageCollect",
	"line" : 591,
	"message" : "Garbage collected LuaAssFile",
	"sec" : 1708694902,
	"section" : "automation/lua",
	"severity" : 4,
	"usec" : 351690900
}{
	"file" : "..\\..\\src\\auto4_lua_assfile.cpp",
	"func" : "Automation4::LuaAssFile::ObjectGarbageCollect",
	"line" : 591,
	"message" : "Garbage collected LuaAssFile",
	"sec" : 1708694902,
	"section" : "automation/lua",
	"severity" : 4,
	"usec" : 351690900
}{
	"file" : "..\\..\\src\\auto4_lua_assfile.cpp",
	"func" : "Automation4::LuaAssFile::ObjectGarbageCollect",
	"line" : 591,
	"message" : "Garbage collected LuaAssFile",
	"sec" : 1708694902,
	"section" : "automation/lua",
	"severity" : 4,
	"usec" : 351690900
}{
	"file" : "..\\..\\src\\auto4_lua_assfile.cpp",
	"func" : "Automation4::LuaAssFile::ObjectGarbageCollect",
	"line" : 591,
	"message" : "Garbage collected LuaAssFile",
	"sec" : 1708694902,
	"section" : "automation/lua",
	"severity" : 4,
	"usec" : 351690900
}{
	"file" : "..\\..\\src\\auto4_lua_assfile.cpp",
	"func" : "Automation4::LuaAssFile::ObjectGarbageCollect",
	"line" : 591,
	"message" : "Garbage collected LuaAssFile",
	"sec" : 1708694902,
	"section" : "automation/lua",
	"severity" : 4,
	"usec" : 351690900
}{
	"file" : "..\\..\\src\\auto4_lua_assfile.cpp",
	"func" : "Automation4::LuaAssFile::ObjectGarbageCollect",
	"line" : 591,
	"message" : "Garbage collected LuaAssFile",
	"sec" : 1708694902,
	"section" : "automation/lua",
	"severity" : 4,
	"usec" : 354318200
}{
	"file" : "..\\..\\src\\auto4_lua_assfile.cpp",
	"func" : "Automation4::LuaAssFile::ObjectGarbageCollect",
	"line" : 591,
	"message" : "Garbage collected LuaAssFile",
	"sec" : 1708694902,
	"section" : "automation/lua",
	"severity" : 4,
	"usec" : 354318200
}{
	"file" : "..\\..\\src\\auto4_lua_assfile.cpp",
	"func" : "Automation4::LuaAssFile::ObjectGarbageCollect",
	"line" : 591,
	"message" : "Garbage collected LuaAssFile",
	"sec" : 1708694902,
	"section" : "automation/lua",
	"severity" : 4,
	"usec" : 354318200
}{
	"file" : "..\\..\\src\\auto4_lua_assfile.cpp",
	"func" : "Automation4::LuaAssFile::ObjectGarbageCollect",
	"line" : 591,
	"message" : "Garbage collected LuaAssFile",
	"sec" : 1708694902,
	"section" : "automation/lua",
	"severity" : 4,
	"usec" : 354318200
}{
	"file" : "..\\..\\src\\auto4_lua_assfile.cpp",
	"func" : "Automation4::LuaAssFile::ObjectGarbageCollect",
	"line" : 591,
	"message" : "Garbage collected LuaAssFile",
	"sec" : 1708694902,
	"section" : "automation/lua",
	"severity" : 4,
	"usec" : 354318200
}{
	"file" : "..\\..\\src\\auto4_lua_assfile.cpp",
	"func" : "Automation4::LuaAssFile::ObjectGarbageCollect",
	"line" : 591,
	"message" : "Garbage collected LuaAssFile",
	"sec" : 1708694902,
	"section" : "automation/lua",
	"severity" : 4,
	"usec" : 354318200
}{
	"file" : "..\\..\\src\\auto4_lua_assfile.cpp",
	"func" : "Automation4::LuaAssFile::ObjectGarbageCollect",
	"line" : 591,
	"message" : "Garbage collected LuaAssFile",
	"sec" : 1708694902,
	"section" : "automation/lua",
	"severity" : 4,
	"usec" : 354318200
}{
	"file" : "..\\..\\src\\auto4_lua_assfile.cpp",
	"func" : "Automation4::LuaAssFile::ObjectGarbageCollect",
	"line" : 591,
	"message" : "Garbage collected LuaAssFile",
	"sec" : 1708694902,
	"section" : "automation/lua",
	"severity" : 4,
	"usec" : 354318200
}{
	"file" : "..\\..\\src\\auto4_lua_assfile.cpp",
	"func" : "Automation4::LuaAssFile::ObjectGarbageCollect",
	"line" : 591,
	"message" : "Garbage collected LuaAssFile",
	"sec" : 1708694902,
	"section" : "automation/lua",
	"severity" : 4,
	"usec" : 354318200
}{
	"file" : "..\\..\\src\\auto4_lua_assfile.cpp",
	"func" : "Automation4::LuaAssFile::ObjectGarbageCollect",
	"line" : 591,
	"message" : "Garbage collected LuaAssFile",
	"sec" : 1708694902,
	"section" : "automation/lua",
	"severity" : 4,
	"usec" : 354318200
}